<?xml version="1.0" encoding="UTF-8"?>
<foxml:digitalObject FEDORA_URI="info:fedora/uuid:0aae4a50-ffb7-11e4-b939-0800200c9a66"
  PID="uuid:0aae4a50-ffb7-11e4-b939-0800200c9a66" VERSION="1.1" xmlns:foxml="info:fedora/fedora-system:def/foxml#"
  xmlns:xsi="http://www.w3.org/2001/XMLSchema-instance" xsi:schemaLocation="info:fedora/fedora-system:def/foxml# http://www.fedora.info/definitions/1/0/foxml1-1.xsd">
  <foxml:objectProperties>
    <foxml:property NAME="info:fedora/fedora-system:def/model#state" VALUE="Active"/>
    <foxml:property NAME="info:fedora/fedora-system:def/model#label" VALUE="   Principy nakládání s radioaktivními odpady   "/>
    <foxml:property NAME="info:fedora/fedora-system:def/model#ownerId" VALUE="fedoraAdmin"/>
    <foxml:property NAME="info:fedora/fedora-system:def/model#createdDate" VALUE="2015-07-15T16:25:16.273Z"/>
    <foxml:property NAME="info:fedora/fedora-system:def/view#lastModifiedDate" VALUE="2017-05-09T07:52:16.438Z"/>
  </foxml:objectProperties>
  <foxml:datastream CONTROL_GROUP="X" FEDORA_URI="info:fedora/uuid:0aae4a50-ffb7-11e4-b939-0800200c9a66/AUDIT"
    ID="AUDIT" STATE="A" VERSIONABLE="false">
    <foxml:datastreamVersion CREATED="2015-07-15T16:25:16.273Z"
      FORMAT_URI="info:fedora/fedora-system:format/xml.fedora.audit" ID="AUDIT.0" LABEL="Audit Trail for this object" MIMETYPE="text/xml">
      <foxml:xmlContent>
        <audit:auditTrail xmlns:audit="info:fedora/fedora-system:def/audit#">
          <audit:record ID="AUDREC1">
            <audit:process type="Fedora API-M"/>
            <audit:action>ingest</audit:action>
            <audit:componentID/>
            <audit:responsibility>fedoraAdmin</audit:responsibility>
            <audit:date>2015-07-15T14:25:22.946Z</audit:date>
            <audit:justification>Initial ingest</audit:justification>
          </audit:record>
          <audit:record ID="AUDREC2">
            <audit:process type="Fedora API-M"/>
            <audit:action>ingest</audit:action>
            <audit:componentID/>
            <audit:responsibility>fedoraAdmin</audit:responsibility>
            <audit:date>2017-05-09T07:52:16.438Z</audit:date>
            <audit:justification>Initial ingest</audit:justification>
          </audit:record>
        </audit:auditTrail>
      </foxml:xmlContent>
    </foxml:datastreamVersion>
  </foxml:datastream>
  <foxml:datastream CONTROL_GROUP="X" FEDORA_URI="info:fedora/uuid:0aae4a50-ffb7-11e4-b939-0800200c9a66/DC" ID="DC"
    STATE="A" VERSIONABLE="false">
    <foxml:datastreamVersion CREATED="2015-07-15T16:25:16.000Z" FORMAT_URI="http://www.openarchives.org/OAI/2.0/oai_dc/"
      ID="DC.0" LABEL="Dublin Core Record for this object" MIMETYPE="text/xml" SIZE="857">
      <foxml:xmlContent>
        <oai_dc:dc xmlns:dc="http://purl.org/dc/elements/1.1/"
          xmlns:oai_dc="http://www.openarchives.org/OAI/2.0/oai_dc/"
          xmlns:xsi="http://www.w3.org/2001/XMLSchema-instance" xsi:schemaLocation="http://www.openarchives.org/OAI/2.0/oai_dc/ http://www.openarchives.org/OAI/2.0/oai_dc.xsd">
          <dc:title>Principy nakládání s radioaktivními odpady</dc:title>
          <dc:creator>Nachmilner Lubomír</dc:creator>
          <dc:subject>udc:621.039.7(075.8)</dc:subject>
          <dc:subject>udc:621.039.58(075.8)</dc:subject>
          <dc:publisher>ČVUT</dc:publisher>
          <dc:date>2000</dc:date>
          <dc:type>model:monograph</dc:type>
          <dc:identifier>uuid:0aae4a50-ffb7-11e4-b939-0800200c9a66</dc:identifier>
          <dc:identifier>contract:F2036</dc:identifier>
          <dc:identifier>isbn:80-01-02258-7</dc:identifier>
          <dc:language>cze</dc:language>
          <dc:rights>policy:private</dc:rights>
        </oai_dc:dc>
      </foxml:xmlContent>
    </foxml:datastreamVersion>
  </foxml:datastream>
  <foxml:datastream CONTROL_GROUP="X" FEDORA_URI="info:fedora/uuid:0aae4a50-ffb7-11e4-b939-0800200c9a66/BIBLIO_MODS"
    ID="BIBLIO_MODS" STATE="A" VERSIONABLE="false">
    <foxml:datastreamVersion CREATED="2015-07-15T16:25:16.000Z" FORMAT_URI="http://www.loc.gov/mods/v3"
      ID="BIBLIO_MODS.0" LABEL="BIBLIO_MODS description of current object" MIMETYPE="text/xml" SIZE="2585">
      <foxml:xmlContent>
        <mods:modsCollection xmlns:mods="http://www.loc.gov/mods/v3">
          <mods:mods version="3.4">
            <mods:identifier type="urn">0aae4a50-ffb7-11e4-b939-0800200c9a66</mods:identifier>
            <mods:identifier type="isbn">80-01-02258-7</mods:identifier>
            <mods:titleInfo>
              <mods:title>
  Principy nakládání s radioaktivními odpady
  </mods:title>
            </mods:titleInfo>
            <mods:subject/>
            <mods:location>
              <mods:physicalLocation>ABA013</mods:physicalLocation>
              <mods:shelfLocator>F 20364</mods:shelfLocator>
            </mods:location>
            <mods:name type="personal">
              <mods:namePart type="family">Nachmilner</mods:namePart>
              <mods:namePart type="given">Lubomír</mods:namePart>
              <mods:role>
                <mods:roleTerm type="code">cre</mods:roleTerm>
                <mods:roleTerm type="text">Author</mods:roleTerm>
              </mods:role>
            </mods:name>
            <mods:typeOfResource>text</mods:typeOfResource>
            <mods:recordInfo>
              <mods:recordIdentifier source="CZ PrSTK">000005013</mods:recordIdentifier>
            </mods:recordInfo>
            <mods:originInfo transliteration="publisher">
              <mods:place>
                <mods:placeTerm type="text">Praha</mods:placeTerm>
              </mods:place>
              <mods:publisher>ČVUT</mods:publisher>
              <mods:dateIssued>2000</mods:dateIssued>
            </mods:originInfo>
            <mods:originInfo>
              <mods:issuance>monographic</mods:issuance>
            </mods:originInfo>
            <mods:language>
              <mods:languageTerm authority="iso639-2b" type="code">cze</mods:languageTerm>
            </mods:language>
            <mods:physicalDescription>
              <mods:extent>49 s.</mods:extent>
              <mods:note>Učeb. texty: Praha, ČVUT, f. jaderná a fyzikálně inženýr.</mods:note>
            </mods:physicalDescription>
            <mods:physicalDescription>
              <mods:note type="action"/>
              <mods:note type="preservationStateOfArt"/>
            </mods:physicalDescription>
            <mods:classification authority="ddc"/>
            <mods:classification authority="udc">621.039.7(075.8)</mods:classification>
            <mods:classification authority="ddc"/>
            <mods:classification authority="udc">621.039.58(075.8)</mods:classification>
          </mods:mods>
        </mods:modsCollection>
      </foxml:xmlContent>
    </foxml:datastreamVersion>
  </foxml:datastream>
  <foxml:datastream CONTROL_GROUP="X" FEDORA_URI="info:fedora/uuid:0aae4a50-ffb7-11e4-b939-0800200c9a66/RELS-EXT"
    ID="RELS-EXT" STATE="A" VERSIONABLE="false">
    <foxml:datastreamVersion CREATED="2015-07-15T16:25:16.000Z" FORMAT_URI="info:fedora/fedora-system:FedoraRELSExt-1.0"
      ID="RELS-EXT.0" LABEL="RDF Statements about this object" MIMETYPE="application/rdf+xml" SIZE="7461">
      <foxml:xmlContent>
        <rdf:RDF xmlns:fedora-model="info:fedora/fedora-system:def/model#"
          xmlns:kramerius="http://www.nsdl.org/ontologies/relationships#"
          xmlns:oai="http://www.openarchives.org/OAI/2.0/" xmlns:rdf="http://www.w3.org/1999/02/22-rdf-syntax-ns#">
          <rdf:Description rdf:about="info:fedora/uuid:0aae4a50-ffb7-11e4-b939-0800200c9a66">
            <fedora-model:hasModel rdf:resource="info:fedora/model:monograph"/>
            <oai:itemID>uuid:0aae4a50-ffb7-11e4-b939-0800200c9a66</oai:itemID>
            <kramerius:hasPage rdf:resource="info:fedora/uuid:39b31bc4-2afd-11e5-88e2-001b63bd97ba"/>
            <kramerius:hasPage rdf:resource="info:fedora/uuid:3a666635-2afd-11e5-88e2-001b63bd97ba"/>
            <kramerius:hasPage rdf:resource="info:fedora/uuid:3adaabd6-2afd-11e5-88e2-001b63bd97ba"/>
            <kramerius:hasPage rdf:resource="info:fedora/uuid:3b357607-2afd-11e5-88e2-001b63bd97ba"/>
            <kramerius:hasPage rdf:resource="info:fedora/uuid:3b979338-2afd-11e5-88e2-001b63bd97ba"/>
            <kramerius:hasPage rdf:resource="info:fedora/uuid:3bf89ef9-2afd-11e5-88e2-001b63bd97ba"/>
            <kramerius:hasPage rdf:resource="info:fedora/uuid:3c5fc53a-2afd-11e5-88e2-001b63bd97ba"/>
            <kramerius:hasPage rdf:resource="info:fedora/uuid:3cc6eb7b-2afd-11e5-88e2-001b63bd97ba"/>
            <kramerius:hasPage rdf:resource="info:fedora/uuid:3d2b047c-2afd-11e5-88e2-001b63bd97ba"/>
            <kramerius:hasPage rdf:resource="info:fedora/uuid:3d90a41d-2afd-11e5-88e2-001b63bd97ba"/>
            <kramerius:hasPage rdf:resource="info:fedora/uuid:3df1afde-2afd-11e5-88e2-001b63bd97ba"/>
            <kramerius:hasPage rdf:resource="info:fedora/uuid:3e56da4f-2afd-11e5-88e2-001b63bd97ba"/>
            <kramerius:hasPage rdf:resource="info:fedora/uuid:3eb267d0-2afd-11e5-88e2-001b63bd97ba"/>
            <kramerius:hasPage rdf:resource="info:fedora/uuid:3f1bb0f1-2afd-11e5-88e2-001b63bd97ba"/>
            <kramerius:hasPage rdf:resource="info:fedora/uuid:3f7df532-2afd-11e5-88e2-001b63bd97ba"/>
            <kramerius:hasPage rdf:resource="info:fedora/uuid:3fe1c013-2afd-11e5-88e2-001b63bd97ba"/>
            <kramerius:hasPage rdf:resource="info:fedora/uuid:40493474-2afd-11e5-88e2-001b63bd97ba"/>
            <kramerius:hasPage rdf:resource="info:fedora/uuid:40aead05-2afd-11e5-88e2-001b63bd97ba"/>
            <kramerius:hasPage rdf:resource="info:fedora/uuid:41162166-2afd-11e5-88e2-001b63bd97ba"/>
            <kramerius:hasPage rdf:resource="info:fedora/uuid:417be817-2afd-11e5-88e2-001b63bd97ba"/>
            <kramerius:hasPage rdf:resource="info:fedora/uuid:41dc7ea8-2afd-11e5-88e2-001b63bd97ba"/>
            <kramerius:hasPage rdf:resource="info:fedora/uuid:4245a0b9-2afd-11e5-88e2-001b63bd97ba"/>
            <kramerius:hasPage rdf:resource="info:fedora/uuid:42a4feca-2afd-11e5-88e2-001b63bd97ba"/>
            <kramerius:hasPage rdf:resource="info:fedora/uuid:430bfdfb-2afd-11e5-88e2-001b63bd97ba"/>
            <kramerius:hasPage rdf:resource="info:fedora/uuid:438091bc-2afd-11e5-88e2-001b63bd97ba"/>
            <kramerius:hasPage rdf:resource="info:fedora/uuid:43e6586d-2afd-11e5-88e2-001b63bd97ba"/>
            <kramerius:hasPage rdf:resource="info:fedora/uuid:444c6d3e-2afd-11e5-88e2-001b63bd97ba"/>
            <kramerius:hasPage rdf:resource="info:fedora/uuid:44b2d02f-2afd-11e5-88e2-001b63bd97ba"/>
            <kramerius:hasPage rdf:resource="info:fedora/uuid:45295fc0-2afd-11e5-88e2-001b63bd97ba"/>
            <kramerius:hasPage rdf:resource="info:fedora/uuid:45962b51-2afd-11e5-88e2-001b63bd97ba"/>
            <kramerius:hasPage rdf:resource="info:fedora/uuid:45fb2eb2-2afd-11e5-88e2-001b63bd97ba"/>
            <kramerius:hasPage rdf:resource="info:fedora/uuid:465f20a3-2afd-11e5-88e2-001b63bd97ba"/>
            <kramerius:hasPage rdf:resource="info:fedora/uuid:46beccd4-2afd-11e5-88e2-001b63bd97ba"/>
            <kramerius:hasPage rdf:resource="info:fedora/uuid:47211115-2afd-11e5-88e2-001b63bd97ba"/>
            <kramerius:hasPage rdf:resource="info:fedora/uuid:4784dbf6-2afd-11e5-88e2-001b63bd97ba"/>
            <kramerius:hasPage rdf:resource="info:fedora/uuid:47ed13a7-2afd-11e5-88e2-001b63bd97ba"/>
            <kramerius:hasPage rdf:resource="info:fedora/uuid:484f30d8-2afd-11e5-88e2-001b63bd97ba"/>
            <kramerius:hasPage rdf:resource="info:fedora/uuid:48b8ef29-2afd-11e5-88e2-001b63bd97ba"/>
            <kramerius:hasPage rdf:resource="info:fedora/uuid:491c92fa-2afd-11e5-88e2-001b63bd97ba"/>
            <kramerius:hasPage rdf:resource="info:fedora/uuid:49869f6b-2afd-11e5-88e2-001b63bd97ba"/>
            <kramerius:hasPage rdf:resource="info:fedora/uuid:49f0abdc-2afd-11e5-88e2-001b63bd97ba"/>
            <kramerius:hasPage rdf:resource="info:fedora/uuid:4a5bc9bd-2afd-11e5-88e2-001b63bd97ba"/>
            <kramerius:hasPage rdf:resource="info:fedora/uuid:4ac38c3e-2afd-11e5-88e2-001b63bd97ba"/>
            <kramerius:hasPage rdf:resource="info:fedora/uuid:4b2e5bff-2afd-11e5-88e2-001b63bd97ba"/>
            <kramerius:hasPage rdf:resource="info:fedora/uuid:4b93d490-2afd-11e5-88e2-001b63bd97ba"/>
            <kramerius:hasPage rdf:resource="info:fedora/uuid:4bf889d1-2afd-11e5-88e2-001b63bd97ba"/>
            <kramerius:hasPage rdf:resource="info:fedora/uuid:4c5576e2-2afd-11e5-88e2-001b63bd97ba"/>
            <kramerius:hasPage rdf:resource="info:fedora/uuid:4cb8f3a3-2afd-11e5-88e2-001b63bd97ba"/>
            <kramerius:hasPage rdf:resource="info:fedora/uuid:4d1d81d4-2afd-11e5-88e2-001b63bd97ba"/>
            <kramerius:hasPage rdf:resource="info:fedora/uuid:4d7b8055-2afd-11e5-88e2-001b63bd97ba"/>
            <kramerius:hasPage rdf:resource="info:fedora/uuid:4dd734e6-2afd-11e5-88e2-001b63bd97ba"/>
            <kramerius:hasPage rdf:resource="info:fedora/uuid:4e30c697-2afd-11e5-88e2-001b63bd97ba"/>
            <kramerius:hasPage rdf:resource="info:fedora/uuid:4e84da08-2afd-11e5-88e2-001b63bd97ba"/>
            <kramerius:hasPage rdf:resource="info:fedora/uuid:4edf2f09-2afd-11e5-88e2-001b63bd97ba"/>
            <kramerius:hasPage rdf:resource="info:fedora/uuid:4f327f2a-2afd-11e5-88e2-001b63bd97ba"/>
            <kramerius:hasPage rdf:resource="info:fedora/uuid:4f9efc9b-2afd-11e5-88e2-001b63bd97ba"/>
            <kramerius:contract>F2036</kramerius:contract>
            <kramerius:policy>policy:private</kramerius:policy>
          </rdf:Description>
        </rdf:RDF>
      </foxml:xmlContent>
    </foxml:datastreamVersion>
  </foxml:datastream>
  <foxml:datastream CONTROL_GROUP="E" FEDORA_URI="info:fedora/uuid:0aae4a50-ffb7-11e4-b939-0800200c9a66/POLICY"
    ID="POLICY" STATE="A" VERSIONABLE="false">
    <foxml:datastreamVersion CREATED="2015-07-15T16:25:16.000Z" ID="POLICY.0" LABEL="" MIMETYPE="application/rdf+xml">
      <foxml:contentLocation REF="http://kramerius1.ntkcz.cz:8080/fedora/get/policy:private/POLICYDEF" TYPE="URL"/>
    </foxml:datastreamVersion>
  </foxml:datastream>
</foxml:digitalObject>
