<?xml version="1.0" encoding="UTF-8"?>
<foxml:digitalObject FEDORA_URI="info:fedora/uuid:4d443e00-0080-11e5-b939-0800200c9a66"
  PID="uuid:4d443e00-0080-11e5-b939-0800200c9a66" VERSION="1.1" xmlns:foxml="info:fedora/fedora-system:def/foxml#"
  xmlns:xsi="http://www.w3.org/2001/XMLSchema-instance" xsi:schemaLocation="info:fedora/fedora-system:def/foxml# http://www.fedora.info/definitions/1/0/foxml1-1.xsd">
  <foxml:objectProperties>
    <foxml:property NAME="info:fedora/fedora-system:def/model#state" VALUE="Active"/>
    <foxml:property NAME="info:fedora/fedora-system:def/model#label" VALUE="   Hydraulika   "/>
    <foxml:property NAME="info:fedora/fedora-system:def/model#ownerId" VALUE="fedoraAdmin"/>
    <foxml:property NAME="info:fedora/fedora-system:def/model#createdDate" VALUE="2015-07-09T15:22:57.381Z"/>
    <foxml:property NAME="info:fedora/fedora-system:def/view#lastModifiedDate" VALUE="2017-05-09T07:53:17.617Z"/>
  </foxml:objectProperties>
  <foxml:datastream CONTROL_GROUP="X" FEDORA_URI="info:fedora/uuid:4d443e00-0080-11e5-b939-0800200c9a66/AUDIT"
    ID="AUDIT" STATE="A" VERSIONABLE="false">
    <foxml:datastreamVersion CREATED="2015-07-09T15:22:57.381Z"
      FORMAT_URI="info:fedora/fedora-system:format/xml.fedora.audit" ID="AUDIT.0" LABEL="Audit Trail for this object" MIMETYPE="text/xml">
      <foxml:xmlContent>
        <audit:auditTrail xmlns:audit="info:fedora/fedora-system:def/audit#">
          <audit:record ID="AUDREC1">
            <audit:process type="Fedora API-M"/>
            <audit:action>ingest</audit:action>
            <audit:componentID/>
            <audit:responsibility>fedoraAdmin</audit:responsibility>
            <audit:date>2015-07-09T13:22:59.012Z</audit:date>
            <audit:justification>Initial ingest</audit:justification>
          </audit:record>
          <audit:record ID="AUDREC2">
            <audit:process type="Fedora API-M"/>
            <audit:action>ingest</audit:action>
            <audit:componentID/>
            <audit:responsibility>fedoraAdmin</audit:responsibility>
            <audit:date>2017-05-09T07:53:17.617Z</audit:date>
            <audit:justification>Initial ingest</audit:justification>
          </audit:record>
        </audit:auditTrail>
      </foxml:xmlContent>
    </foxml:datastreamVersion>
  </foxml:datastream>
  <foxml:datastream CONTROL_GROUP="X" FEDORA_URI="info:fedora/uuid:4d443e00-0080-11e5-b939-0800200c9a66/DC" ID="DC"
    STATE="A" VERSIONABLE="false">
    <foxml:datastreamVersion CREATED="2015-07-09T15:22:57.000Z" FORMAT_URI="http://www.openarchives.org/OAI/2.0/oai_dc/"
      ID="DC.0" LABEL="Dublin Core Record for this object" MIMETYPE="text/xml" SIZE="892">
      <foxml:xmlContent>
        <oai_dc:dc xmlns:dc="http://purl.org/dc/elements/1.1/"
          xmlns:oai_dc="http://www.openarchives.org/OAI/2.0/oai_dc/"
          xmlns:xsi="http://www.w3.org/2001/XMLSchema-instance" xsi:schemaLocation="http://www.openarchives.org/OAI/2.0/oai_dc/ http://www.openarchives.org/OAI/2.0/oai_dc.xsd">
          <dc:title>Hydraulika</dc:title>
          <dc:creator>Krešl Jiří</dc:creator>
          <dc:subject>udc:532(075.8)</dc:subject>
          <dc:subject>udc:556.34(075.8)</dc:subject>
          <dc:subject>udc:556.536(075.8)</dc:subject>
          <dc:publisher>Mendelova zemědělská a lesnická univerzita</dc:publisher>
          <dc:date>2001</dc:date>
          <dc:type>model:monograph</dc:type>
          <dc:identifier>uuid:4d443e00-0080-11e5-b939-0800200c9a66</dc:identifier>
          <dc:identifier>contract:F2045</dc:identifier>
          <dc:identifier>isbn:80-7157-490-2</dc:identifier>
          <dc:language>cze</dc:language>
          <dc:rights>policy:private</dc:rights>
        </oai_dc:dc>
      </foxml:xmlContent>
    </foxml:datastreamVersion>
  </foxml:datastream>
  <foxml:datastream CONTROL_GROUP="X" FEDORA_URI="info:fedora/uuid:4d443e00-0080-11e5-b939-0800200c9a66/BIBLIO_MODS"
    ID="BIBLIO_MODS" STATE="A" VERSIONABLE="false">
    <foxml:datastreamVersion CREATED="2015-07-09T15:22:57.000Z" FORMAT_URI="http://www.loc.gov/mods/v3"
      ID="BIBLIO_MODS.0" LABEL="BIBLIO_MODS description of current object" MIMETYPE="text/xml" SIZE="2704">
      <foxml:xmlContent>
        <mods:modsCollection xmlns:mods="http://www.loc.gov/mods/v3">
          <mods:mods version="3.4">
            <mods:identifier type="urn">4d443e00-0080-11e5-b939-0800200c9a66</mods:identifier>
            <mods:identifier type="isbn">80-7157-490-2</mods:identifier>
            <mods:titleInfo>
              <mods:title>
  Hydraulika
  </mods:title>
            </mods:titleInfo>
            <mods:subject/>
            <mods:location>
              <mods:physicalLocation>ABA013</mods:physicalLocation>
              <mods:shelfLocator>F 20451</mods:shelfLocator>
            </mods:location>
            <mods:name type="personal">
              <mods:namePart type="family">Krešl</mods:namePart>
              <mods:namePart type="given">Jiří</mods:namePart>
              <mods:role>
                <mods:roleTerm type="code">cre</mods:roleTerm>
                <mods:roleTerm type="text">Author</mods:roleTerm>
              </mods:role>
            </mods:name>
            <mods:typeOfResource>text</mods:typeOfResource>
            <mods:recordInfo>
              <mods:recordIdentifier source="CZ PrSTK">000005846</mods:recordIdentifier>
            </mods:recordInfo>
            <mods:originInfo transliteration="publisher">
              <mods:place>
                <mods:placeTerm type="text">Brno</mods:placeTerm>
              </mods:place>
              <mods:publisher>Mendelova zemědělská a lesnická univerzita</mods:publisher>
              <mods:dateIssued>2001</mods:dateIssued>
            </mods:originInfo>
            <mods:originInfo>
              <mods:issuance>monographic</mods:issuance>
            </mods:originInfo>
            <mods:language>
              <mods:languageTerm authority="iso639-2b" type="code">cze</mods:languageTerm>
            </mods:language>
            <mods:physicalDescription>
              <mods:extent>59 s., [7] s. obr.</mods:extent>
              <mods:note>Učeb. texty: Brno, MZLU</mods:note>
            </mods:physicalDescription>
            <mods:physicalDescription>
              <mods:note type="action"/>
              <mods:note type="preservationStateOfArt"/>
            </mods:physicalDescription>
            <mods:classification authority="ddc"/>
            <mods:classification authority="udc">532(075.8)</mods:classification>
            <mods:classification authority="ddc"/>
            <mods:classification authority="udc">556.34(075.8)</mods:classification>
            <mods:classification authority="ddc"/>
            <mods:classification authority="udc">556.536(075.8)</mods:classification>
          </mods:mods>
        </mods:modsCollection>
      </foxml:xmlContent>
    </foxml:datastreamVersion>
  </foxml:datastream>
  <foxml:datastream CONTROL_GROUP="X" FEDORA_URI="info:fedora/uuid:4d443e00-0080-11e5-b939-0800200c9a66/RELS-EXT"
    ID="RELS-EXT" STATE="A" VERSIONABLE="false">
    <foxml:datastreamVersion CREATED="2015-07-09T15:22:57.000Z" FORMAT_URI="info:fedora/fedora-system:FedoraRELSExt-1.0"
      ID="RELS-EXT.0" LABEL="RDF Statements about this object" MIMETYPE="application/rdf+xml" SIZE="9881">
      <foxml:xmlContent>
        <rdf:RDF xmlns:fedora-model="info:fedora/fedora-system:def/model#"
          xmlns:kramerius="http://www.nsdl.org/ontologies/relationships#"
          xmlns:oai="http://www.openarchives.org/OAI/2.0/" xmlns:rdf="http://www.w3.org/1999/02/22-rdf-syntax-ns#">
          <rdf:Description rdf:about="info:fedora/uuid:4d443e00-0080-11e5-b939-0800200c9a66">
            <fedora-model:hasModel rdf:resource="info:fedora/model:monograph"/>
            <oai:itemID>uuid:4d443e00-0080-11e5-b939-0800200c9a66</oai:itemID>
            <kramerius:hasPage rdf:resource="info:fedora/uuid:819da1e3-263d-11e5-a6e8-001b63bd97ba"/>
            <kramerius:hasPage rdf:resource="info:fedora/uuid:822ce994-263d-11e5-a6e8-001b63bd97ba"/>
            <kramerius:hasPage rdf:resource="info:fedora/uuid:8282f8d5-263d-11e5-a6e8-001b63bd97ba"/>
            <kramerius:hasPage rdf:resource="info:fedora/uuid:82d97d46-263d-11e5-a6e8-001b63bd97ba"/>
            <kramerius:hasPage rdf:resource="info:fedora/uuid:832bbbf7-263d-11e5-a6e8-001b63bd97ba"/>
            <kramerius:hasPage rdf:resource="info:fedora/uuid:8386ad38-263d-11e5-a6e8-001b63bd97ba"/>
            <kramerius:hasPage rdf:resource="info:fedora/uuid:83e288d9-263d-11e5-a6e8-001b63bd97ba"/>
            <kramerius:hasPage rdf:resource="info:fedora/uuid:8440d57a-263d-11e5-a6e8-001b63bd97ba"/>
            <kramerius:hasPage rdf:resource="info:fedora/uuid:849b9fab-263d-11e5-a6e8-001b63bd97ba"/>
            <kramerius:hasPage rdf:resource="info:fedora/uuid:84fa135c-263d-11e5-a6e8-001b63bd97ba"/>
            <kramerius:hasPage rdf:resource="info:fedora/uuid:8558870d-263d-11e5-a6e8-001b63bd97ba"/>
            <kramerius:hasPage rdf:resource="info:fedora/uuid:85b489be-263d-11e5-a6e8-001b63bd97ba"/>
            <kramerius:hasPage rdf:resource="info:fedora/uuid:86123a1f-263d-11e5-a6e8-001b63bd97ba"/>
            <kramerius:hasPage rdf:resource="info:fedora/uuid:866f7550-263d-11e5-a6e8-001b63bd97ba"/>
            <kramerius:hasPage rdf:resource="info:fedora/uuid:86d08111-263d-11e5-a6e8-001b63bd97ba"/>
            <kramerius:hasPage rdf:resource="info:fedora/uuid:873424e2-263d-11e5-a6e8-001b63bd97ba"/>
            <kramerius:hasPage rdf:resource="info:fedora/uuid:879075b3-263d-11e5-a6e8-001b63bd97ba"/>
            <kramerius:hasPage rdf:resource="info:fedora/uuid:87ea7c94-263d-11e5-a6e8-001b63bd97ba"/>
            <kramerius:hasPage rdf:resource="info:fedora/uuid:883df3c5-263d-11e5-a6e8-001b63bd97ba"/>
            <kramerius:hasPage rdf:resource="info:fedora/uuid:88971046-263d-11e5-a6e8-001b63bd97ba"/>
            <kramerius:hasPage rdf:resource="info:fedora/uuid:88f18c57-263d-11e5-a6e8-001b63bd97ba"/>
            <kramerius:hasPage rdf:resource="info:fedora/uuid:894e0438-263d-11e5-a6e8-001b63bd97ba"/>
            <kramerius:hasPage rdf:resource="info:fedora/uuid:89a68479-263d-11e5-a6e8-001b63bd97ba"/>
            <kramerius:hasPage rdf:resource="info:fedora/uuid:89fd7e1a-263d-11e5-a6e8-001b63bd97ba"/>
            <kramerius:hasPage rdf:resource="info:fedora/uuid:8a5784fb-263d-11e5-a6e8-001b63bd97ba"/>
            <kramerius:hasPage rdf:resource="info:fedora/uuid:8ab8dedc-263d-11e5-a6e8-001b63bd97ba"/>
            <kramerius:hasPage rdf:resource="info:fedora/uuid:8b1ad4fd-263d-11e5-a6e8-001b63bd97ba"/>
            <kramerius:hasPage rdf:resource="info:fedora/uuid:8b7c07ce-263d-11e5-a6e8-001b63bd97ba"/>
            <kramerius:hasPage rdf:resource="info:fedora/uuid:8be1a76f-263d-11e5-a6e8-001b63bd97ba"/>
            <kramerius:hasPage rdf:resource="info:fedora/uuid:8c568950-263d-11e5-a6e8-001b63bd97ba"/>
            <kramerius:hasPage rdf:resource="info:fedora/uuid:8cb15381-263d-11e5-a6e8-001b63bd97ba"/>
            <kramerius:hasPage rdf:resource="info:fedora/uuid:8d128652-263d-11e5-a6e8-001b63bd97ba"/>
            <kramerius:hasPage rdf:resource="info:fedora/uuid:8d73e033-263d-11e5-a6e8-001b63bd97ba"/>
            <kramerius:hasPage rdf:resource="info:fedora/uuid:8dced174-263d-11e5-a6e8-001b63bd97ba"/>
            <kramerius:hasPage rdf:resource="info:fedora/uuid:8e299ba5-263d-11e5-a6e8-001b63bd97ba"/>
            <kramerius:hasPage rdf:resource="info:fedora/uuid:8e817fa6-263d-11e5-a6e8-001b63bd97ba"/>
            <kramerius:hasPage rdf:resource="info:fedora/uuid:8ed5e137-263d-11e5-a6e8-001b63bd97ba"/>
            <kramerius:hasPage rdf:resource="info:fedora/uuid:8f2dc538-263d-11e5-a6e8-001b63bd97ba"/>
            <kramerius:hasPage rdf:resource="info:fedora/uuid:8f842299-263d-11e5-a6e8-001b63bd97ba"/>
            <kramerius:hasPage rdf:resource="info:fedora/uuid:8fdace1a-263d-11e5-a6e8-001b63bd97ba"/>
            <kramerius:hasPage rdf:resource="info:fedora/uuid:90328b0b-263d-11e5-a6e8-001b63bd97ba"/>
            <kramerius:hasPage rdf:resource="info:fedora/uuid:908d071c-263d-11e5-a6e8-001b63bd97ba"/>
            <kramerius:hasPage rdf:resource="info:fedora/uuid:910396ad-263d-11e5-a6e8-001b63bd97ba"/>
            <kramerius:hasPage rdf:resource="info:fedora/uuid:9177400e-263d-11e5-a6e8-001b63bd97ba"/>
            <kramerius:hasPage rdf:resource="info:fedora/uuid:91df028f-263d-11e5-a6e8-001b63bd97ba"/>
            <kramerius:hasPage rdf:resource="info:fedora/uuid:9243b7d0-263d-11e5-a6e8-001b63bd97ba"/>
            <kramerius:hasPage rdf:resource="info:fedora/uuid:92a5adf1-263d-11e5-a6e8-001b63bd97ba"/>
            <kramerius:hasPage rdf:resource="info:fedora/uuid:92ff1892-263d-11e5-a6e8-001b63bd97ba"/>
            <kramerius:hasPage rdf:resource="info:fedora/uuid:935af433-263d-11e5-a6e8-001b63bd97ba"/>
            <kramerius:hasPage rdf:resource="info:fedora/uuid:93b4fb14-263d-11e5-a6e8-001b63bd97ba"/>
            <kramerius:hasPage rdf:resource="info:fedora/uuid:94123645-263d-11e5-a6e8-001b63bd97ba"/>
            <kramerius:hasPage rdf:resource="info:fedora/uuid:946649b6-263d-11e5-a6e8-001b63bd97ba"/>
            <kramerius:hasPage rdf:resource="info:fedora/uuid:94bd6a67-263d-11e5-a6e8-001b63bd97ba"/>
            <kramerius:hasPage rdf:resource="info:fedora/uuid:95191ef8-263d-11e5-a6e8-001b63bd97ba"/>
            <kramerius:hasPage rdf:resource="info:fedora/uuid:9571ed59-263d-11e5-a6e8-001b63bd97ba"/>
            <kramerius:hasPage rdf:resource="info:fedora/uuid:95cc696a-263d-11e5-a6e8-001b63bd97ba"/>
            <kramerius:hasPage rdf:resource="info:fedora/uuid:962510bb-263d-11e5-a6e8-001b63bd97ba"/>
            <kramerius:hasPage rdf:resource="info:fedora/uuid:96809e3c-263d-11e5-a6e8-001b63bd97ba"/>
            <kramerius:hasPage rdf:resource="info:fedora/uuid:96dbb68d-263d-11e5-a6e8-001b63bd97ba"/>
            <kramerius:hasPage rdf:resource="info:fedora/uuid:973b149e-263d-11e5-a6e8-001b63bd97ba"/>
            <kramerius:hasPage rdf:resource="info:fedora/uuid:9799af5f-263d-11e5-a6e8-001b63bd97ba"/>
            <kramerius:hasPage rdf:resource="info:fedora/uuid:97f2cbe0-263d-11e5-a6e8-001b63bd97ba"/>
            <kramerius:hasPage rdf:resource="info:fedora/uuid:984b9a41-263d-11e5-a6e8-001b63bd97ba"/>
            <kramerius:hasPage rdf:resource="info:fedora/uuid:98ac57e2-263d-11e5-a6e8-001b63bd97ba"/>
            <kramerius:hasPage rdf:resource="info:fedora/uuid:98ff32d3-263d-11e5-a6e8-001b63bd97ba"/>
            <kramerius:hasPage rdf:resource="info:fedora/uuid:9953e284-263d-11e5-a6e8-001b63bd97ba"/>
            <kramerius:hasPage rdf:resource="info:fedora/uuid:99a44c75-263d-11e5-a6e8-001b63bd97ba"/>
            <kramerius:hasPage rdf:resource="info:fedora/uuid:99fdde26-263d-11e5-a6e8-001b63bd97ba"/>
            <kramerius:hasPage rdf:resource="info:fedora/uuid:9a554cf7-263d-11e5-a6e8-001b63bd97ba"/>
            <kramerius:hasPage rdf:resource="info:fedora/uuid:9aace2d8-263d-11e5-a6e8-001b63bd97ba"/>
            <kramerius:hasPage rdf:resource="info:fedora/uuid:9b05b139-263d-11e5-a6e8-001b63bd97ba"/>
            <kramerius:hasPage rdf:resource="info:fedora/uuid:9b5aaf0a-263d-11e5-a6e8-001b63bd97ba"/>
            <kramerius:hasPage rdf:resource="info:fedora/uuid:9bb1cfbb-263d-11e5-a6e8-001b63bd97ba"/>
            <kramerius:hasPage rdf:resource="info:fedora/uuid:9c0a4ffc-263d-11e5-a6e8-001b63bd97ba"/>
            <kramerius:hasPage rdf:resource="info:fedora/uuid:9c5dee3d-263d-11e5-a6e8-001b63bd97ba"/>
            <kramerius:hasPage rdf:resource="info:fedora/uuid:9cae7f3e-263d-11e5-a6e8-001b63bd97ba"/>
            <kramerius:contract>F2045</kramerius:contract>
            <kramerius:policy>policy:private</kramerius:policy>
          </rdf:Description>
        </rdf:RDF>
      </foxml:xmlContent>
    </foxml:datastreamVersion>
  </foxml:datastream>
  <foxml:datastream CONTROL_GROUP="E" FEDORA_URI="info:fedora/uuid:4d443e00-0080-11e5-b939-0800200c9a66/POLICY"
    ID="POLICY" STATE="A" VERSIONABLE="false">
    <foxml:datastreamVersion CREATED="2015-07-09T15:22:57.000Z" ID="POLICY.0" LABEL="" MIMETYPE="application/rdf+xml">
      <foxml:contentLocation REF="http://kramerius1.ntkcz.cz:8080/fedora/get/policy:private/POLICYDEF" TYPE="URL"/>
    </foxml:datastreamVersion>
  </foxml:datastream>
</foxml:digitalObject>
